navband_visited.py
williballenthin_navband_visited_ida_plugin-0.1.0.dist-info/METADATA
williballenthin_navband_visited_ida_plugin-0.1.0.dist-info/WHEEL
williballenthin_navband_visited_ida_plugin-0.1.0.dist-info/entry_points.txt
williballenthin_navband_visited_ida_plugin-0.1.0.dist-info/top_level.txt
williballenthin_navband_visited_ida_plugin-0.1.0.dist-info/RECORD
