Metadata-Version: 2.4
Name: williballenthin-navband-visited-ida-plugin
Version: 0.1.0
Summary: IDA Pro plugin to highlight visited addresses in the navigation band.
Author-email: Willi Ballenthin <willi.ballenthin@gmail.com>
License-Expression: Apache-2.0
Requires-Python: >=3.9
